singlecon/__init__.py
singlecon/template_config.py
singlecon-0.0.6.dist-info/METADATA
singlecon-0.0.6.dist-info/WHEEL
singlecon-0.0.6.dist-info/RECORD
